{
"instructions_readme": "1) Open Chrome, 2) go to chrome://tracing, 3) click Load, 4) navigate to this file.",

"traceEvents":[
{ "pid": 1, "tid": 1, "ph": "M", "name": "thread_name", "args": { "name": "" } },
{ "pid": 1, "tid": 1, "ts": 1980.9000492095947, "dur": 31964529.296875, "ph": "X", "name": "il2cpp.exe", "args": { "durationMS": 31964.529296875, "detail": "" } },
{ "pid": 1, "tid": 1, "ts": 110042.39654541016, "dur": 31856289.0625, "ph": "X", "name": "ConvertAssemblies", "args": { "durationMS": 31856.2890625, "detail": "" } },
{ "pid": 1, "tid": 1, "ts": 412334.6862792969, "dur": 604353.8818359375, "ph": "X", "name": "Collect assemblies to convert", "args": { "durationMS": 604.3538818359375, "detail": "" } },
{ "pid": 1, "tid": 1, "ts": 1017529.2358398438, "dur": 255374.0997314453, "ph": "X", "name": "RegisterCorlib", "args": { "durationMS": 255.3740997314453, "detail": "" } },
{ "pid": 1, "tid": 1, "ts": 1273757.2021484375, "dur": 160964.7979736328, "ph": "X", "name": "PreProcessIL", "args": { "durationMS": 160.9647979736328, "detail": "" } },
{ "pid": 1, "tid": 1, "ts": 1273758.1787109375, "dur": 63754.10079956055, "ph": "X", "name": "Inject base types and finalizers into COM and Windows Runtime types", "args": { "durationMS": 63.75410079956055, "detail": "" } },
{ "pid": 1, "tid": 1, "ts": 1293780.3955078125, "dur": 39574.89776611328, "ph": "X", "name": "ModifyCOMAndWindowsRuntimeTypes in assembly", "args": { "durationMS": 39.57489776611328, "detail": "mscorlib" } },
{ "pid": 1, "tid": 1, "ts": 1334937.98828125, "dur": 1906.1000347137451, "ph": "X", "name": "ModifyCOMAndWindowsRuntimeTypes in assembly", "args": { "durationMS": 1.9061000347137451, "detail": "UnityEngine.UI" } },
{ "pid": 1, "tid": 1, "ts": 1336846.19140625, "dur": 592.2999978065491, "ph": "X", "name": "ModifyCOMAndWindowsRuntimeTypes in assembly", "args": { "durationMS": 0.5922999978065491, "detail": "Unity.TextMeshPro" } },
{ "pid": 1, "tid": 1, "ts": 1337512.5732421875, "dur": 97208.3969116211, "ph": "X", "name": "ApplyDefaultMarshalAsAttribute", "args": { "durationMS": 97.2083969116211, "detail": "" } },
{ "pid": 1, "tid": 1, "ts": 1338428.5888671875, "dur": 72196.70104980469, "ph": "X", "name": "ApplyDefaultMarshalAsAttributeVisitor in assembly", "args": { "durationMS": 72.19670104980469, "detail": "mscorlib" } },
{ "pid": 1, "tid": 1, "ts": 1410808.10546875, "dur": 6763.599872589111, "ph": "X", "name": "ApplyDefaultMarshalAsAttributeVisitor in assembly", "args": { "durationMS": 6.763599872589111, "detail": "System" } },
{ "pid": 1, "tid": 1, "ts": 1417574.0966796875, "dur": 452.8999924659729, "ph": "X", "name": "ApplyDefaultMarshalAsAttributeVisitor in assembly", "args": { "durationMS": 0.4528999924659729, "detail": "System.Core" } },
{ "pid": 1, "tid": 1, "ts": 1418279.1748046875, "dur": 4735.000133514404, "ph": "X", "name": "ApplyDefaultMarshalAsAttributeVisitor in assembly", "args": { "durationMS": 4.735000133514404, "detail": "UnityEngine.CoreModule" } },
{ "pid": 1, "tid": 1, "ts": 1423898.0712890625, "dur": 601.4000177383423, "ph": "X", "name": "ApplyDefaultMarshalAsAttributeVisitor in assembly", "args": { "durationMS": 0.6014000177383423, "detail": "UnityEngine.IMGUIModule" } },
{ "pid": 1, "tid": 1, "ts": 1424952.63671875, "dur": 391.49999618530273, "ph": "X", "name": "ApplyDefaultMarshalAsAttributeVisitor in assembly", "args": { "durationMS": 0.39149999618530273, "detail": "UnityEngine.GameCenterModule" } },
{ "pid": 1, "tid": 1, "ts": 1425731.0791015625, "dur": 4147.299766540527, "ph": "X", "name": "ApplyDefaultMarshalAsAttributeVisitor in assembly", "args": { "durationMS": 4.147299766540527, "detail": "UnityEngine.UI" } },
{ "pid": 1, "tid": 1, "ts": 1429880.4931640625, "dur": 4583.000183105469, "ph": "X", "name": "ApplyDefaultMarshalAsAttributeVisitor in assembly", "args": { "durationMS": 4.583000183105469, "detail": "Unity.TextMeshPro" } },
{ "pid": 1, "tid": 1, "ts": 1435277.9541015625, "dur": 117214.00451660156, "ph": "X", "name": "WriteResources", "args": { "durationMS": 117.21400451660156, "detail": "" } },
{ "pid": 1, "tid": 1, "ts": 1553354.98046875, "dur": 1153783.8134765625, "ph": "X", "name": "CopyEtcFolder", "args": { "durationMS": 1153.7838134765625, "detail": "" } },
{ "pid": 1, "tid": 1, "ts": 2710187.744140625, "dur": 346137.2985839844, "ph": "X", "name": "PreProcessStage", "args": { "durationMS": 346.1372985839844, "detail": "" } },
{ "pid": 1, "tid": 1, "ts": 3074171.875, "dur": 3520.4999446868896, "ph": "X", "name": "Debugger Sequence Points", "args": { "durationMS": 3.5204999446868896, "detail": "" } },
{ "pid": 1, "tid": 1, "ts": 3080841.552734375, "dur": 1265093.6279296875, "ph": "X", "name": "Generics Collection", "args": { "durationMS": 1265.0936279296875, "detail": "" } },
{ "pid": 1, "tid": 1, "ts": 3080842.529296875, "dur": 1133151.85546875, "ph": "X", "name": "GenericsCollector.Collect", "args": { "durationMS": 1133.15185546875, "detail": "" } },
{ "pid": 1, "tid": 1, "ts": 3083171.38671875, "dur": 52820.899963378906, "ph": "X", "name": "GenericCodeFlowGraphCollector.Collect", "args": { "durationMS": 52.820899963378906, "detail": "" } },
{ "pid": 1, "tid": 1, "ts": 3083172.36328125, "dur": 51353.69873046875, "ph": "X", "name": "GenericCodeFlowGraphCollector.GetTypesAndMethodsForAnalysis", "args": { "durationMS": 51.35369873046875, "detail": "" } },
{ "pid": 1, "tid": 1, "ts": 4213994.62890625, "dur": 128289.81018066406, "ph": "X", "name": "CollectGenericVirtualMethods.Collect", "args": { "durationMS": 128.28981018066406, "detail": "" } },
{ "pid": 1, "tid": 1, "ts": 4342285.64453125, "dur": 2923.3999252319336, "ph": "X", "name": "AddExtraTypes", "args": { "durationMS": 2.9233999252319336, "detail": "" } },
{ "pid": 1, "tid": 1, "ts": 4345936.03515625, "dur": 2977.60009765625, "ph": "X", "name": "Add Windows Runtime type names", "args": { "durationMS": 2.97760009765625, "detail": "" } },
{ "pid": 1, "tid": 1, "ts": 4351933.59375, "dur": 16422349.609375, "ph": "X", "name": "AllAssemblyConversion", "args": { "durationMS": 16422.349609375, "detail": "" } },
{ "pid": 1, "tid": 1, "ts": 4353574.70703125, "dur": 8924105.46875, "ph": "X", "name": "Convert assembly non-generic methods", "args": { "durationMS": 8924.10546875, "detail": "mscorlib" } },
{ "pid": 1, "tid": 1, "ts": 13277715.8203125, "dur": 15076.399803161621, "ph": "X", "name": "Convert assembly non-generic methods", "args": { "durationMS": 15.076399803161621, "detail": "System.Configuration" } },
{ "pid": 1, "tid": 1, "ts": 13292800.78125, "dur": 32378.597259521484, "ph": "X", "name": "Convert assembly non-generic methods", "args": { "durationMS": 32.378597259521484, "detail": "Mono.Security" } },
{ "pid": 1, "tid": 1, "ts": 13325189.453125, "dur": 7779.099941253662, "ph": "X", "name": "Convert assembly non-generic methods", "args": { "durationMS": 7.779099941253662, "detail": "System.Xml" } },
{ "pid": 1, "tid": 1, "ts": 13332977.5390625, "dur": 791488.0981445312, "ph": "X", "name": "Convert assembly non-generic methods", "args": { "durationMS": 791.4880981445312, "detail": "System" } },
{ "pid": 1, "tid": 1, "ts": 14124474.609375, "dur": 11355.899810791016, "ph": "X", "name": "Convert assembly non-generic methods", "args": { "durationMS": 11.355899810791016, "detail": "System.Core" } },
{ "pid": 1, "tid": 1, "ts": 14135837.890625, "dur": 44429.100036621094, "ph": "X", "name": "Convert assembly non-generic methods", "args": { "durationMS": 44.429100036621094, "detail": "UnityEngine.SharedInternalsModule" } },
{ "pid": 1, "tid": 1, "ts": 14180275.390625, "dur": 825314.0258789062, "ph": "X", "name": "Convert assembly non-generic methods", "args": { "durationMS": 825.3140258789062, "detail": "UnityEngine.CoreModule" } },
{ "pid": 1, "tid": 1, "ts": 15005599.609375, "dur": 9020.1997756958, "ph": "X", "name": "Convert assembly non-generic methods", "args": { "durationMS": 9.0201997756958, "detail": "UnityEngine.GridModule" } },
{ "pid": 1, "tid": 1, "ts": 15014629.8828125, "dur": 38697.601318359375, "ph": "X", "name": "Convert assembly non-generic methods", "args": { "durationMS": 38.697601318359375, "detail": "UnityEngine.InputLegacyModule" } },
{ "pid": 1, "tid": 1, "ts": 15053340.8203125, "dur": 42773.30017089844, "ph": "X", "name": "Convert assembly non-generic methods", "args": { "durationMS": 42.77330017089844, "detail": "UnityEngine.Physics2DModule" } },
{ "pid": 1, "tid": 1, "ts": 15096124.0234375, "dur": 51007.29751586914, "ph": "X", "name": "Convert assembly non-generic methods", "args": { "durationMS": 51.00729751586914, "detail": "UnityEngine.TextRenderingModule" } },
{ "pid": 1, "tid": 1, "ts": 15147138.671875, "dur": 60043.800354003906, "ph": "X", "name": "Convert assembly non-generic methods", "args": { "durationMS": 60.043800354003906, "detail": "UnityEngine.AnimationModule" } },
{ "pid": 1, "tid": 1, "ts": 15207193.359375, "dur": 176900.5889892578, "ph": "X", "name": "Convert assembly non-generic methods", "args": { "durationMS": 176.9005889892578, "detail": "UnityEngine.IMGUIModule" } },
{ "pid": 1, "tid": 1, "ts": 15384102.5390625, "dur": 12757.30037689209, "ph": "X", "name": "Convert assembly non-generic methods", "args": { "durationMS": 12.75730037689209, "detail": "UnityEngine.PhysicsModule" } },
{ "pid": 1, "tid": 1, "ts": 15396867.1875, "dur": 9823.800086975098, "ph": "X", "name": "Convert assembly non-generic methods", "args": { "durationMS": 9.823800086975098, "detail": "UnityEngine.SpriteShapeModule" } },
{ "pid": 1, "tid": 1, "ts": 15406707.03125, "dur": 8199.799537658691, "ph": "X", "name": "Convert assembly non-generic methods", "args": { "durationMS": 8.199799537658691, "detail": "UnityEngine.TilemapModule" } },
{ "pid": 1, "tid": 1, "ts": 15414914.0625, "dur": 43378.700256347656, "ph": "X", "name": "Convert assembly non-generic methods", "args": { "durationMS": 43.378700256347656, "detail": "UnityEngine.UIModule" } },
{ "pid": 1, "tid": 1, "ts": 15458300.78125, "dur": 28368.898391723633, "ph": "X", "name": "Convert assembly non-generic methods", "args": { "durationMS": 28.368898391723633, "detail": "UnityEngine.AudioModule" } },
{ "pid": 1, "tid": 1, "ts": 15486677.734375, "dur": 83854.29382324219, "ph": "X", "name": "Convert assembly non-generic methods", "args": { "durationMS": 83.85429382324219, "detail": "UnityEngine.GameCenterModule" } },
{ "pid": 1, "tid": 1, "ts": 15570541.015625, "dur": 24747.800827026367, "ph": "X", "name": "Convert assembly non-generic methods", "args": { "durationMS": 24.747800827026367, "detail": "UnityEngine.ParticleSystemModule" } },
{ "pid": 1, "tid": 1, "ts": 15595295.8984375, "dur": 66272.59826660156, "ph": "X", "name": "Convert assembly non-generic methods", "args": { "durationMS": 66.27259826660156, "detail": "UnityEngine.TextCoreModule" } },
{ "pid": 1, "tid": 1, "ts": 15661577.1484375, "dur": 1962531.6162109375, "ph": "X", "name": "Convert assembly non-generic methods", "args": { "durationMS": 1962.5316162109375, "detail": "UnityEngine.UI" } },
{ "pid": 1, "tid": 1, "ts": 17624117.1875, "dur": 3068273.193359375, "ph": "X", "name": "Convert assembly non-generic methods", "args": { "durationMS": 3068.273193359375, "detail": "Unity.TextMeshPro" } },
{ "pid": 1, "tid": 1, "ts": 20692402.34375, "dur": 8091.19987487793, "ph": "X", "name": "Convert assembly non-generic methods", "args": { "durationMS": 8.09119987487793, "detail": "UnityEngine" } },
{ "pid": 1, "tid": 1, "ts": 20700500, "dur": 73772.59826660156, "ph": "X", "name": "Convert assembly non-generic methods", "args": { "durationMS": 73.77259826660156, "detail": "Assembly-CSharp" } },
{ "pid": 1, "tid": 1, "ts": 20774953.125, "dur": 5944210.44921875, "ph": "X", "name": "WriteGenerics", "args": { "durationMS": 5944.21044921875, "detail": "" } },
{ "pid": 1, "tid": 1, "ts": 20779470.703125, "dur": 1218699.5849609375, "ph": "X", "name": "GenericInstanceMethods", "args": { "durationMS": 1218.6995849609375, "detail": "" } },
{ "pid": 1, "tid": 1, "ts": 21998173.828125, "dur": 4317331.54296875, "ph": "X", "name": "GenericInstanceTypes", "args": { "durationMS": 4317.33154296875, "detail": "" } },
{ "pid": 1, "tid": 1, "ts": 26316048.828125, "dur": 403091.97998046875, "ph": "X", "name": "GenericComDefinitions", "args": { "durationMS": 403.09197998046875, "detail": "" } },
{ "pid": 1, "tid": 1, "ts": 26720164.0625, "dur": 2831.0000896453857, "ph": "X", "name": "Executable Processing", "args": { "durationMS": 2.8310000896453857, "detail": "" } },
{ "pid": 1, "tid": 1, "ts": 26724074.21875, "dur": 591072.998046875, "ph": "X", "name": "MetadataCollector", "args": { "durationMS": 591.072998046875, "detail": "" } },
{ "pid": 1, "tid": 1, "ts": 26730080.078125, "dur": 77135.29968261719, "ph": "X", "name": "UpdateEmptyTokens", "args": { "durationMS": 77.13529968261719, "detail": "" } },
{ "pid": 1, "tid": 1, "ts": 26811089.84375, "dur": 25073.101043701172, "ph": "X", "name": "ValidateTokens", "args": { "durationMS": 25.073101043701172, "detail": "" } },
{ "pid": 1, "tid": 1, "ts": 27317244.140625, "dur": 4425.3997802734375, "ph": "X", "name": "Write COM Callable Wrappers", "args": { "durationMS": 4.4253997802734375, "detail": "" } },
{ "pid": 1, "tid": 1, "ts": 27320781.25, "dur": 880.6999921798706, "ph": "X", "name": "Collect implemented projected interfaces by COM Callable Wrappers", "args": { "durationMS": 0.8806999921798706, "detail": "" } },
{ "pid": 1, "tid": 1, "ts": 27322164.0625, "dur": 2280.9998989105225, "ph": "X", "name": "Write Windows Runtime Factories", "args": { "durationMS": 2.2809998989105225, "detail": "" } },
{ "pid": 1, "tid": 1, "ts": 27326150.390625, "dur": 4634719.23828125, "ph": "X", "name": "Metadata", "args": { "durationMS": 4634.71923828125, "detail": "Global" } },
{ "pid": 1, "tid": 1, "ts": 27421302.734375, "dur": 718317.0776367188, "ph": "X", "name": "Il2CppAttributes.cpp", "args": { "durationMS": 718.3170776367188, "detail": "" } },
{ "pid": 1, "tid": 1, "ts": 28341009.765625, "dur": 62714.50424194336, "ph": "X", "name": "UnresolvedVirtualCallStubs.cpp", "args": { "durationMS": 62.71450424194336, "detail": "" } },
{ "pid": 1, "tid": 1, "ts": 28406425.78125, "dur": 1057494.7509765625, "ph": "X", "name": "WriteCodeRegistration", "args": { "durationMS": 1057.4947509765625, "detail": "" } },
{ "pid": 1, "tid": 1, "ts": 28406494.140625, "dur": 188531.99768066406, "ph": "X", "name": "mscorlib_CodeGen.c", "args": { "durationMS": 188.53199768066406, "detail": "" } },
{ "pid": 1, "tid": 1, "ts": 28500976.5625, "dur": 13220.999717712402, "ph": "X", "name": "GenericContextCollector", "args": { "durationMS": 13.220999717712402, "detail": "Collect" } },
{ "pid": 1, "tid": 1, "ts": 28595066.40625, "dur": 7704.599857330322, "ph": "X", "name": "System.Configuration_CodeGen.c", "args": { "durationMS": 7.704599857330322, "detail": "" } },
{ "pid": 1, "tid": 1, "ts": 28602820.3125, "dur": 7894.100189208984, "ph": "X", "name": "Mono.Security_CodeGen.c", "args": { "durationMS": 7.894100189208984, "detail": "" } },
{ "pid": 1, "tid": 1, "ts": 28610755.859375, "dur": 7581.7999839782715, "ph": "X", "name": "System.Xml_CodeGen.c", "args": { "durationMS": 7.5817999839782715, "detail": "" } },
{ "pid": 1, "tid": 1, "ts": 28618388.671875, "dur": 19942.19970703125, "ph": "X", "name": "System_CodeGen.c", "args": { "durationMS": 19.94219970703125, "detail": "" } },
{ "pid": 1, "tid": 1, "ts": 28638380.859375, "dur": 9196.900367736816, "ph": "X", "name": "System.Core_CodeGen.c", "args": { "durationMS": 9.196900367736816, "detail": "" } },
{ "pid": 1, "tid": 1, "ts": 28639097.65625, "dur": 345.6000089645386, "ph": "X", "name": "GenericContextCollector", "args": { "durationMS": 0.3456000089645386, "detail": "Collect" } },
{ "pid": 1, "tid": 1, "ts": 28647621.09375, "dur": 8545.599937438965, "ph": "X", "name": "UnityEngine.SharedInternalsModule_CodeGen.c", "args": { "durationMS": 8.545599937438965, "detail": "" } },
{ "pid": 1, "tid": 1, "ts": 28656208.984375, "dur": 35653.499603271484, "ph": "X", "name": "UnityEngine.CoreModule_CodeGen.c", "args": { "durationMS": 35.653499603271484, "detail": "" } },
{ "pid": 1, "tid": 1, "ts": 28671324.21875, "dur": 1149.7000455856323, "ph": "X", "name": "GenericContextCollector", "args": { "durationMS": 1.1497000455856323, "detail": "Collect" } },
{ "pid": 1, "tid": 1, "ts": 28691906.25, "dur": 7528.39994430542, "ph": "X", "name": "UnityEngine.GridModule_CodeGen.c", "args": { "durationMS": 7.52839994430542, "detail": "" } },
{ "pid": 1, "tid": 1, "ts": 28699476.5625, "dur": 8219.400405883789, "ph": "X", "name": "UnityEngine.InputLegacyModule_CodeGen.c", "args": { "durationMS": 8.219400405883789, "detail": "" } },
{ "pid": 1, "tid": 1, "ts": 28707755.859375, "dur": 8529.500007629395, "ph": "X", "name": "UnityEngine.Physics2DModule_CodeGen.c", "args": { "durationMS": 8.529500007629395, "detail": "" } },
{ "pid": 1, "tid": 1, "ts": 28716337.890625, "dur": 9234.399795532227, "ph": "X", "name": "UnityEngine.TextRenderingModule_CodeGen.c", "args": { "durationMS": 9.234399795532227, "detail": "" } },
{ "pid": 1, "tid": 1, "ts": 28725625, "dur": 8924.90005493164, "ph": "X", "name": "UnityEngine.AnimationModule_CodeGen.c", "args": { "durationMS": 8.92490005493164, "detail": "" } },
{ "pid": 1, "tid": 1, "ts": 28734603.515625, "dur": 10700.699806213379, "ph": "X", "name": "UnityEngine.IMGUIModule_CodeGen.c", "args": { "durationMS": 10.700699806213379, "detail": "" } },
{ "pid": 1, "tid": 1, "ts": 28745361.328125, "dur": 7683.599948883057, "ph": "X", "name": "UnityEngine.PhysicsModule_CodeGen.c", "args": { "durationMS": 7.683599948883057, "detail": "" } },
{ "pid": 1, "tid": 1, "ts": 28753093.75, "dur": 7110.899925231934, "ph": "X", "name": "UnityEngine.SpriteShapeModule_CodeGen.c", "args": { "durationMS": 7.110899925231934, "detail": "" } },
{ "pid": 1, "tid": 1, "ts": 28760267.578125, "dur": 7536.499977111816, "ph": "X", "name": "UnityEngine.TilemapModule_CodeGen.c", "args": { "durationMS": 7.536499977111816, "detail": "" } },
{ "pid": 1, "tid": 1, "ts": 28767882.8125, "dur": 8998.100280761719, "ph": "X", "name": "UnityEngine.UIModule_CodeGen.c", "args": { "durationMS": 8.998100280761719, "detail": "" } },
{ "pid": 1, "tid": 1, "ts": 28776925.78125, "dur": 8338.99974822998, "ph": "X", "name": "UnityEngine.AudioModule_CodeGen.c", "args": { "durationMS": 8.33899974822998, "detail": "" } },
{ "pid": 1, "tid": 1, "ts": 28785343.75, "dur": 11322.89981842041, "ph": "X", "name": "UnityEngine.GameCenterModule_CodeGen.c", "args": { "durationMS": 11.32289981842041, "detail": "" } },
{ "pid": 1, "tid": 1, "ts": 28796714.84375, "dur": 7183.899879455566, "ph": "X", "name": "UnityEngine.ParticleSystemModule_CodeGen.c", "args": { "durationMS": 7.183899879455566, "detail": "" } },
{ "pid": 1, "tid": 1, "ts": 28803947.265625, "dur": 9538.900375366211, "ph": "X", "name": "UnityEngine.TextCoreModule_CodeGen.c", "args": { "durationMS": 9.538900375366211, "detail": "" } },
{ "pid": 1, "tid": 1, "ts": 28813539.0625, "dur": 38361.99951171875, "ph": "X", "name": "UnityEngine.UI_CodeGen.c", "args": { "durationMS": 38.36199951171875, "detail": "" } },
{ "pid": 1, "tid": 1, "ts": 28830226.5625, "dur": 571.9000101089478, "ph": "X", "name": "GenericContextCollector", "args": { "durationMS": 0.5719000101089478, "detail": "Collect" } },
{ "pid": 1, "tid": 1, "ts": 28851955.078125, "dur": 36470.30258178711, "ph": "X", "name": "Unity.TextMeshPro_CodeGen.c", "args": { "durationMS": 36.47030258178711, "detail": "" } },
{ "pid": 1, "tid": 1, "ts": 28867287.109375, "dur": 1435.5000257492065, "ph": "X", "name": "GenericContextCollector", "args": { "durationMS": 1.4355000257492065, "detail": "Collect" } },
{ "pid": 1, "tid": 1, "ts": 28888482.421875, "dur": 8132.499694824219, "ph": "X", "name": "UnityEngine_CodeGen.c", "args": { "durationMS": 8.132499694824219, "detail": "" } },
{ "pid": 1, "tid": 1, "ts": 28896664.0625, "dur": 8695.899963378906, "ph": "X", "name": "Assembly-CSharp_CodeGen.c", "args": { "durationMS": 8.695899963378906, "detail": "" } },
{ "pid": 1, "tid": 1, "ts": 28908210.9375, "dur": 10303.000450134277, "ph": "X", "name": "Il2CppReversePInvokeWrapperTable.cpp", "args": { "durationMS": 10.303000450134277, "detail": "" } },
{ "pid": 1, "tid": 1, "ts": 28919142.578125, "dur": 188319.7021484375, "ph": "X", "name": "Il2CppGenericMethodPointerTable.cpp", "args": { "durationMS": 188.3197021484375, "detail": "" } },
{ "pid": 1, "tid": 1, "ts": 29108011.71875, "dur": 295832.3974609375, "ph": "X", "name": "Il2CppInvokerTable.cpp", "args": { "durationMS": 295.8323974609375, "detail": "" } },
{ "pid": 1, "tid": 1, "ts": 29405845.703125, "dur": 36818.20297241211, "ph": "X", "name": "Il2CppInteropDataTable.cpp", "args": { "durationMS": 36.81820297241211, "detail": "" } },
{ "pid": 1, "tid": 1, "ts": 29455119.140625, "dur": 8790.499687194824, "ph": "X", "name": "Il2CppCodeRegistration.cpp", "args": { "durationMS": 8.790499687194824, "detail": "" } },
{ "pid": 1, "tid": 1, "ts": 29463919.921875, "dur": 2496947.998046875, "ph": "X", "name": "WriteMetadata", "args": { "durationMS": 2496.947998046875, "detail": "" } },
{ "pid": 1, "tid": 1, "ts": 29505699.21875, "dur": 427265.4113769531, "ph": "X", "name": "Il2CppMetadataUsage.c", "args": { "durationMS": 427.2654113769531, "detail": "" } },
{ "pid": 1, "tid": 1, "ts": 29664935.546875, "dur": 5374.499797821045, "ph": "X", "name": "Metadata", "args": { "durationMS": 5.374499797821045, "detail": "Collect string literals" } },
{ "pid": 1, "tid": 1, "ts": 29954015.625, "dur": 38288.89846801758, "ph": "X", "name": "Il2CppGenericClassTable.c", "args": { "durationMS": 38.28889846801758, "detail": "" } },
{ "pid": 1, "tid": 1, "ts": 29992349.609375, "dur": 49815.70053100586, "ph": "X", "name": "Il2CppGenericInstDefinitions.c", "args": { "durationMS": 49.81570053100586, "detail": "" } },
{ "pid": 1, "tid": 1, "ts": 30042251.953125, "dur": 377379.5166015625, "ph": "X", "name": "Il2CppGenericMethodTable.c", "args": { "durationMS": 377.3795166015625, "detail": "" } },
{ "pid": 1, "tid": 1, "ts": 30419664.0625, "dur": 272168.9147949219, "ph": "X", "name": "Il2CppTypeDefinitions.c", "args": { "durationMS": 272.1689147949219, "detail": "" } },
{ "pid": 1, "tid": 1, "ts": 30691878.90625, "dur": 104943.39752197266, "ph": "X", "name": "Il2CppGenericMethodDefinitions.c", "args": { "durationMS": 104.94339752197266, "detail": "" } },
{ "pid": 1, "tid": 1, "ts": 30796822.265625, "dur": 683259.27734375, "ph": "X", "name": "CompilerCalculateTypeValues", "args": { "durationMS": 683.25927734375, "detail": "" } },
{ "pid": 1, "tid": 1, "ts": 31480115.234375, "dur": 13162.599563598633, "ph": "X", "name": "Il2CppMetadataRegistration.c", "args": { "durationMS": 13.162599563598633, "detail": "" } },
{ "pid": 1, "tid": 1, "ts": 31582685.546875, "dur": 11449.399948120117, "ph": "X", "name": "StringLiteralWriter", "args": { "durationMS": 11.449399948120117, "detail": "" } },
{ "pid": 1, "tid": 1, "ts": 31594867.1875, "dur": 46065.799713134766, "ph": "X", "name": "Metadata Strings", "args": { "durationMS": 46.065799713134766, "detail": "" } },
{ "pid": 1, "tid": 1, "ts": 31640957.03125, "dur": 9062.5, "ph": "X", "name": "Events", "args": { "durationMS": 9.0625, "detail": "" } },
{ "pid": 1, "tid": 1, "ts": 31650025.390625, "dur": 13615.900993347168, "ph": "X", "name": "Properties", "args": { "durationMS": 13.615900993347168, "detail": "" } },
{ "pid": 1, "tid": 1, "ts": 31663646.484375, "dur": 79664.29901123047, "ph": "X", "name": "Methods", "args": { "durationMS": 79.66429901123047, "detail": "" } },
{ "pid": 1, "tid": 1, "ts": 31743314.453125, "dur": 1920.4000234603882, "ph": "X", "name": "Parameter Default Values", "args": { "durationMS": 1.9204000234603882, "detail": "" } },
{ "pid": 1, "tid": 1, "ts": 31745238.28125, "dur": 2858.9999675750732, "ph": "X", "name": "Field Default Values", "args": { "durationMS": 2.8589999675750732, "detail": "" } },
{ "pid": 1, "tid": 1, "ts": 31748099.609375, "dur": 1506.8000555038452, "ph": "X", "name": "Field and Parameter Default Values Data", "args": { "durationMS": 1.5068000555038452, "detail": "" } },
{ "pid": 1, "tid": 1, "ts": 31749609.375, "dur": 1690.000057220459, "ph": "X", "name": "Field Marshaled Sizes", "args": { "durationMS": 1.690000057220459, "detail": "" } },
{ "pid": 1, "tid": 1, "ts": 31751300.78125, "dur": 16427.501678466797, "ph": "X", "name": "Parameters", "args": { "durationMS": 16.427501678466797, "detail": "" } },
{ "pid": 1, "tid": 1, "ts": 31767730.46875, "dur": 10440.099716186523, "ph": "X", "name": "Fields", "args": { "durationMS": 10.440099716186523, "detail": "" } },
{ "pid": 1, "tid": 1, "ts": 31778173.828125, "dur": 3019.399881362915, "ph": "X", "name": "Generic Parameters", "args": { "durationMS": 3.019399881362915, "detail": "" } },
{ "pid": 1, "tid": 1, "ts": 31781195.3125, "dur": 1206.5999507904053, "ph": "X", "name": "Generic Parameter Constraints", "args": { "durationMS": 1.2065999507904053, "detail": "" } },
{ "pid": 1, "tid": 1, "ts": 31782404.296875, "dur": 2753.9000511169434, "ph": "X", "name": "Generic Containers", "args": { "durationMS": 2.7539000511169434, "detail": "" } },
{ "pid": 1, "tid": 1, "ts": 31785160.15625, "dur": 1017.0999765396118, "ph": "X", "name": "Nested Types", "args": { "durationMS": 1.0170999765396118, "detail": "" } },
{ "pid": 1, "tid": 1, "ts": 31786179.6875, "dur": 728.600025177002, "ph": "X", "name": "Interfaces", "args": { "durationMS": 0.728600025177002, "detail": "" } },
{ "pid": 1, "tid": 1, "ts": 31786910.15625, "dur": 2221.8000888824463, "ph": "X", "name": "VTables", "args": { "durationMS": 2.2218000888824463, "detail": "" } },
{ "pid": 1, "tid": 1, "ts": 31789130.859375, "dur": 2951.900005340576, "ph": "X", "name": "Interface Offsets", "args": { "durationMS": 2.951900005340576, "detail": "" } },
{ "pid": 1, "tid": 1, "ts": 31792087.890625, "dur": 63185.79864501953, "ph": "X", "name": "Type Definitions", "args": { "durationMS": 63.18579864501953, "detail": "" } },
{ "pid": 1, "tid": 1, "ts": 31855273.4375, "dur": 8195.899963378906, "ph": "X", "name": "Images", "args": { "durationMS": 8.195899963378906, "detail": "" } },
{ "pid": 1, "tid": 1, "ts": 31863472.65625, "dur": 3843.6999320983887, "ph": "X", "name": "Assemblies", "args": { "durationMS": 3.8436999320983887, "detail": "" } },
{ "pid": 1, "tid": 1, "ts": 31867318.359375, "dur": 1327.6000022888184, "ph": "X", "name": "Metadata Usage Lists", "args": { "durationMS": 1.3276000022888184, "detail": "" } },
{ "pid": 1, "tid": 1, "ts": 31868650.390625, "dur": 2908.9999198913574, "ph": "X", "name": "Metadata Usage Pairs", "args": { "durationMS": 2.9089999198913574, "detail": "" } },
{ "pid": 1, "tid": 1, "ts": 31871558.59375, "dur": 595.4999923706055, "ph": "X", "name": "Field Refs", "args": { "durationMS": 0.5954999923706055, "detail": "" } },
{ "pid": 1, "tid": 1, "ts": 31872156.25, "dur": 1434.8000288009644, "ph": "X", "name": "Referenced Assemblies", "args": { "durationMS": 1.4348000288009644, "detail": "" } },
{ "pid": 1, "tid": 1, "ts": 31873593.75, "dur": 2746.7000484466553, "ph": "X", "name": "Attribute Types Ranges", "args": { "durationMS": 2.7467000484466553, "detail": "" } },
{ "pid": 1, "tid": 1, "ts": 31876343.75, "dur": 891.700029373169, "ph": "X", "name": "Attribute Types", "args": { "durationMS": 0.891700029373169, "detail": "" } },
{ "pid": 1, "tid": 1, "ts": 31877234.375, "dur": 507.099986076355, "ph": "X", "name": "Unresolved Virtual Call Parameter Types", "args": { "durationMS": 0.507099986076355, "detail": "" } },
{ "pid": 1, "tid": 1, "ts": 31877742.1875, "dur": 1671.5999841690063, "ph": "X", "name": "Unresolved Virtual Call Parameter Ranges", "args": { "durationMS": 1.6715999841690063, "detail": "" } },
{ "pid": 1, "tid": 1, "ts": 31879417.96875, "dur": 941.7999982833862, "ph": "X", "name": "Windows Runtime type names", "args": { "durationMS": 0.9417999982833862, "detail": "" } },
{ "pid": 1, "tid": 1, "ts": 31880361.328125, "dur": 2201.200008392334, "ph": "X", "name": "Exported Types", "args": { "durationMS": 2.201200008392334, "detail": "" } },
{ "pid": 1, "tid": 1, "ts": 31961599.609375, "dur": 2940.0999546051025, "ph": "X", "name": "CompletionPhase", "args": { "durationMS": 2.9400999546051025, "detail": "" } }
],
"meta_datetime": "01/19/2021 19:09:23",
"meta_command_line": "\"C:\\Program Files\\Unity\\Hub\\Editor\\2020.1.10f1\\Editor\\Data\\il2cpp\\build\\deploy\\netcoreapp3.0\\il2cpp.dll\" --convert-to-cpp --emit-null-checks --enable-array-bounds-check --dotnetprofile=unityaot --incremental-g-c-time-slice=3 --avoid-dynamic-library-copy --profiler-report \"--map-file-parser=C:/Program Files/Unity/Hub/Editor/2020.1.10f1/Editor/Data/Tools/MapFileParser/MapFileParser.exe\" \"--directory=F:/mcast level 4 2nd yesr/pcg/kyleattardMSD42CAssignment/kyle_attard_4.2C/Temp/StagingArea/Data/Managed\" \"--generatedcppdir=F:/mcast level 4 2nd yesr/pcg/kyleattardMSD42CAssignment/kyle_attard_4.2C/Temp/il2cppOutput/il2cppOutput\"",
"meta_command_line_args": "C:\\Program Files\\Unity\\Hub\\Editor\\2020.1.10f1\\Editor\\Data\\il2cpp\\build\\deploy\\netcoreapp3.0\\il2cpp.dll --convert-to-cpp --emit-null-checks --enable-array-bounds-check --dotnetprofile=unityaot --incremental-g-c-time-slice=3 --avoid-dynamic-library-copy --profiler-report --map-file-parser=C:/Program Files/Unity/Hub/Editor/2020.1.10f1/Editor/Data/Tools/MapFileParser/MapFileParser.exe --directory=F:/mcast level 4 2nd yesr/pcg/kyleattardMSD42CAssignment/kyle_attard_4.2C/Temp/StagingArea/Data/Managed --generatedcppdir=F:/mcast level 4 2nd yesr/pcg/kyleattardMSD42CAssignment/kyle_attard_4.2C/Temp/il2cppOutput/il2cppOutput",
"meta_user_name": "Kyle",
"meta_os_version": "Microsoft Windows NT 6.2.9200.0",
"meta_cpu_count": "4"}
